docker_db/__init__.py
docker_db/cassandra_db.py
docker_db/containers.py
docker_db/mongo_db.py
docker_db/mssql_db.py
docker_db/mysql_db.py
docker_db/postgres_db.py
docker_db/utils.py
py_dockerdb-0.8.0.dist-info/licenses/LICENSE
py_dockerdb-0.8.0.dist-info/METADATA
py_dockerdb-0.8.0.dist-info/WHEEL
py_dockerdb-0.8.0.dist-info/top_level.txt
py_dockerdb-0.8.0.dist-info/RECORD
