Metadata-Version: 2.4
Name: py-dockerdb
Version: 0.8.0
Summary: Python package for working with databases in Docker containers
Home-page: https://github.com/amadou-6e/docker-db.git
Author: Amadou Wolfgang Cisse
Author-email: amadou.6e@googlemail.com
Classifier: Programming Language :: Python :: 3
Classifier: Operating System :: OS Independent
Classifier: Topic :: Database
Classifier: Topic :: Software Development :: Libraries :: Python Modules
Requires-Python: >=3.6
License-File: LICENSE
Requires-Dist: psycopg2-binary
Requires-Dist: docker
Requires-Dist: pytest
Requires-Dist: pymongo
Requires-Dist: pydantic
Requires-Dist: setuptools
Requires-Dist: docker
Requires-Dist: pyodbc
Requires-Dist: mysql-connector-python
Requires-Dist: pydos2unix
Dynamic: author
Dynamic: author-email
Dynamic: classifier
Dynamic: description-content-type
Dynamic: home-page
Dynamic: license-file
Dynamic: requires-dist
Dynamic: requires-python
Dynamic: summary
